shared_dependencies/__init__.py
shared_dependencies/encrypt.py
shared_dependencies/fake_redis.py
shared_dependencies/func_utils.py
shared_dependencies/http_client.py
shared_dependencies/models.py
shared_dependencies/sentry.py
shared_dependencies/session.py
shared_dependencies-1.2.1.dist-info/WHEEL
shared_dependencies-1.2.1.dist-info/METADATA
shared_dependencies-1.2.1.dist-info/RECORD
