Metadata-Version: 2.1
Name: shared-dependencies
Version: 1.2.1
Summary: 
Author: Jean-Charles Bouchaud
Author-email: jeancharles-b@evidenceb.com
Requires-Python: >=3.9
Classifier: Programming Language :: Python :: 3
Classifier: Programming Language :: Python :: 3.9
Classifier: Programming Language :: Python :: 3.10
Classifier: Programming Language :: Python :: 3.11
Requires-Dist: PyJWT (>=2.6.0,<3.0.0)
Requires-Dist: asttokens (>=2.1.0,<3.0.0)
Requires-Dist: colorama (>=0.4.6,<0.5.0)
Requires-Dist: cryptography (>=40.0.2,<41.0.0)
Requires-Dist: executing (>=1.2.0,<2.0.0)
Requires-Dist: httpx (>=0.24.0,<0.25.0)
Requires-Dist: pure-eval (>=0.2.2,<0.3.0)
Requires-Dist: pycryptodome (>=3.15.0,<4.0.0)
Requires-Dist: pydantic[dotenv] (>=1.10.2,<2.0.0)
Requires-Dist: redis (>=4.3.5,<5.0.0)
Requires-Dist: sentry-sdk (>=1.11.0,<2.0.0)
Requires-Dist: tenacity (>=8.1.0,<9.0.0)
